alaudaapi/__ini__.py
alaudaapi/__version__.py
alaudaapi/api_requests.py
alaudaapi/base_request.py
alaudaapi/exceptions.py
alaudaapi/loadfile.py
alaudaapi/log.py
alaudaapi/settings.py
alaudaapi/utils.py
alaudaapi-0.1.1.dist-info/METADATA
alaudaapi-0.1.1.dist-info/WHEEL
alaudaapi-0.1.1.dist-info/top_level.txt
alaudaapi-0.1.1.dist-info/RECORD
