Metadata-Version: 2.1
Name: alaudaapi
Version: 0.1.1
Summary: just test
Home-page: https://bitbucket.org/mathildetech/alauda-api-automation/src
Author: hchan
Author-email: hchan@alauda.io
License: UNKNOWN
Platform: UNKNOWN
Classifier: Development Status :: 5 - Production/Stable
Classifier: Intended Audience :: Developers
Classifier: Natural Language :: English
Classifier: Programming Language :: Python
Classifier: Programming Language :: Python :: 3
Classifier: Programming Language :: Python :: 3.4
Classifier: Programming Language :: Python :: 3.5
Classifier: Programming Language :: Python :: 3.6
Classifier: Programming Language :: Python :: 3.7
Classifier: Programming Language :: Python :: Implementation :: CPython
Requires-Python: >=3.0, !=3.0.*, !=3.1.*, !=3.2.*, !=3.3*
Requires-Dist: pyyaml
Requires-Dist: jinja2
